setup.py
topsis_yotest/__init__.py
topsis_yotest.egg-info/PKG-INFO
topsis_yotest.egg-info/SOURCES.txt
topsis_yotest.egg-info/dependency_links.txt
topsis_yotest.egg-info/entry_points.txt
topsis_yotest.egg-info/requires.txt
topsis_yotest.egg-info/top_level.txt