Metadata-Version: 2.1
Name: topsis-yotest
Version: 0.0.7
Summary: A Python package implementing TOPSIS technique.
Home-page: https://pypi.org/project/topsis-yotest/0.0.1/
Author: Yash Shukla
Author-email: yash981815@gmail.comm
License: MIT
Platform: UNKNOWN
Classifier: License :: OSI Approved :: MIT License
Classifier: Programming Language :: Python :: 3
Classifier: Programming Language :: Python :: 3.4
Classifier: Programming Language :: Python :: 3.5
Classifier: Programming Language :: Python :: 3.6
Classifier: Programming Language :: Python :: 3.7
